Workbook

Sheet 取引
A1: 売上・経費 取引入力
A2: 黄色欄に入力。事業割合は経費のみ有効(空欄=100)。家事按分後の額は1円未満切捨て。
A4: 日付 | B4: 区分 | C4: 勘定科目 | D4: 摘要 | E4: 金額(税込) | F4: 事業割合(%) | G4: 計上額 | H4: 月
A5: 46032 | B5: 売上 | D5: サンプル案件A(ダミー) | E5: 110000 | G5: =IF(OR(E5="",B5=""),0,IF(B5="売上",E5,SIGN(E5)*INT(ABS(E5)*IF(F5="",100,F5)/100))) | H5: =IF(A5="","",IF(YEAR(A5)=年間集計!$B$2,MONTH(A5),0))
A6: 46037 | B6: 経費 | C6: 通信費 | D6: インターネット回線(ダミー) | E6: 5500 | F6: 50 | G6: =IF(OR(E6="",B6=""),0,IF(B6="売上",E6,SIGN(E6)*INT(ABS(E6)*IF(F6="",100,F6)/100))) | H6: =IF(A6="","",IF(YEAR(A6)=年間集計!$B$2,MONTH(A6),0))
A7: 46056 | B7: 経費 | C7: 消耗品費 | D7: 文具(ダミー) | E7: 1234 | G7: =IF(OR(E7="",B7=""),0,IF(B7="売上",E7,SIGN(E7)*INT(ABS(E7)*IF(F7="",100,F7)/100))) | H7: =IF(A7="","",IF(YEAR(A7)=年間集計!$B$2,MONTH(A7),0))
G8: =IF(OR(E8="",B8=""),0,IF(B8="売上",E8,SIGN(E8)*INT(ABS(E8)*IF(F8="",100,F8)/100))) | H8: =IF(A8="","",IF(YEAR(A8)=年間集計!$B$2,MONTH(A8),0))
G9: =IF(OR(E9="",B9=""),0,IF(B9="売上",E9,SIGN(E9)*INT(ABS(E9)*IF(F9="",100,F9)/100))) | H9: =IF(A9="","",IF(YEAR(A9)=年間集計!$B$2,MONTH(A9),0))
G10: =IF(OR(E10="",B10=""),0,IF(B10="売上",E10,SIGN(E10)*INT(ABS(E10)*IF(F10="",100,F10)/100))) | H10: =IF(A10="","",IF(YEAR(A10)=年間集計!$B$2,MONTH(A10),0))
G11: =IF(OR(E11="",B11=""),0,IF(B11="売上",E11,SIGN(E11)*INT(ABS(E11)*IF(F11="",100,F11)/100))) | H11: =IF(A11="","",IF(YEAR(A11)=年間集計!$B$2,MONTH(A11),0))
G12: =IF(OR(E12="",B12=""),0,IF(B12="売上",E12,SIGN(E12)*INT(ABS(E12)*IF(F12="",100,F12)/100))) | H12: =IF(A12="","",IF(YEAR(A12)=年間集計!$B$2,MONTH(A12),0))
G13: =IF(OR(E13="",B13=""),0,IF(B13="売上",E13,SIGN(E13)*INT(ABS(E13)*IF(F13="",100,F13)/100))) | H13: =IF(A13="","",IF(YEAR(A13)=年間集計!$B$2,MONTH(A13),0))
G14: =IF(OR(E14="",B14=""),0,IF(B14="売上",E14,SIGN(E14)*INT(ABS(E14)*IF(F14="",100,F14)/100))) | H14: =IF(A14="","",IF(YEAR(A14)=年間集計!$B$2,MONTH(A14),0))
G15: =IF(OR(E15="",B15=""),0,IF(B15="売上",E15,SIGN(E15)*INT(ABS(E15)*IF(F15="",100,F15)/100))) | H15: =IF(A15="","",IF(YEAR(A15)=年間集計!$B$2,MONTH(A15),0))
G16: =IF(OR(E16="",B16=""),0,IF(B16="売上",E16,SIGN(E16)*INT(ABS(E16)*IF(F16="",100,F16)/100))) | H16: =IF(A16="","",IF(YEAR(A16)=年間集計!$B$2,MONTH(A16),0))
G17: =IF(OR(E17="",B17=""),0,IF(B17="売上",E17,SIGN(E17)*INT(ABS(E17)*IF(F17="",100,F17)/100))) | H17: =IF(A17="","",IF(YEAR(A17)=年間集計!$B$2,MONTH(A17),0))
G18: =IF(OR(E18="",B18=""),0,IF(B18="売上",E18,SIGN(E18)*INT(ABS(E18)*IF(F18="",100,F18)/100))) | H18: =IF(A18="","",IF(YEAR(A18)=年間集計!$B$2,MONTH(A18),0))
G19: =IF(OR(E19="",B19=""),0,IF(B19="売上",E19,SIGN(E19)*INT(ABS(E19)*IF(F19="",100,F19)/100))) | H19: =IF(A19="","",IF(YEAR(A19)=年間集計!$B$2,MONTH(A19),0))
... G304: =IF(OR(E304="",B304=""),0,IF(B304="売上",E304,SIGN(E304)*INT(ABS(E304)*IF(F304="",100,F304)/100))) | H304: =IF(A304="","",IF(YEAR(A304)=年間集計!$B$2,MONTH(A304),0))

Sheet 年間集計
A1: 年間集計
A2: 対象年(西暦) | B2: 2026
A4: 月 | B4: 売上 | C4: 経費(按分後) | D4: 差引
A5: 1 | B5: =SUMIFS(取引!$G$5:$G$304,取引!$B$5:$B$304,"売上",取引!$H$5:$H$304,A5) | C5: =SUMIFS(取引!$G$5:$G$304,取引!$B$5:$B$304,"経費",取引!$H$5:$H$304,A5) | D5: =B5-C5
A6: 2 | B6: =SUMIFS(取引!$G$5:$G$304,取引!$B$5:$B$304,"売上",取引!$H$5:$H$304,A6) | C6: =SUMIFS(取引!$G$5:$G$304,取引!$B$5:$B$304,"経費",取引!$H$5:$H$304,A6) | D6: =B6-C6
A7: 3 | B7: =SUMIFS(取引!$G$5:$G$304,取引!$B$5:$B$304,"売上",取引!$H$5:$H$304,A7) | C7: =SUMIFS(取引!$G$5:$G$304,取引!$B$5:$B$304,"経費",取引!$H$5:$H$304,A7) | D7: =B7-C7
A8: 4 | B8: =SUMIFS(取引!$G$5:$G$304,取引!$B$5:$B$304,"売上",取引!$H$5:$H$304,A8) | C8: =SUMIFS(取引!$G$5:$G$304,取引!$B$5:$B$304,"経費",取引!$H$5:$H$304,A8) | D8: =B8-C8
A9: 5 | B9: =SUMIFS(取引!$G$5:$G$304,取引!$B$5:$B$304,"売上",取引!$H$5:$H$304,A9) | C9: =SUMIFS(取引!$G$5:$G$304,取引!$B$5:$B$304,"経費",取引!$H$5:$H$304,A9) | D9: =B9-C9
A10: 6 | B10: =SUMIFS(取引!$G$5:$G$304,取引!$B$5:$B$304,"売上",取引!$H$5:$H$304,A10) | C10: =SUMIFS(取引!$G$5:$G$304,取引!$B$5:$B$304,"経費",取引!$H$5:$H$304,A10) | D10: =B10-C10
A11: 7 | B11: =SUMIFS(取引!$G$5:$G$304,取引!$B$5:$B$304,"売上",取引!$H$5:$H$304,A11) | C11: =SUMIFS(取引!$G$5:$G$304,取引!$B$5:$B$304,"経費",取引!$H$5:$H$304,A11) | D11: =B11-C11
A12: 8 | B12: =SUMIFS(取引!$G$5:$G$304,取引!$B$5:$B$304,"売上",取引!$H$5:$H$304,A12) | C12: =SUMIFS(取引!$G$5:$G$304,取引!$B$5:$B$304,"経費",取引!$H$5:$H$304,A12) | D12: =B12-C12
A13: 9 | B13: =SUMIFS(取引!$G$5:$G$304,取引!$B$5:$B$304,"売上",取引!$H$5:$H$304,A13) | C13: =SUMIFS(取引!$G$5:$G$304,取引!$B$5:$B$304,"経費",取引!$H$5:$H$304,A13) | D13: =B13-C13
A14: 10 | B14: =SUMIFS(取引!$G$5:$G$304,取引!$B$5:$B$304,"売上",取引!$H$5:$H$304,A14) | C14: =SUMIFS(取引!$G$5:$G$304,取引!$B$5:$B$304,"経費",取引!$H$5:$H$304,A14) | D14: =B14-C14
A15: 11 | B15: =SUMIFS(取引!$G$5:$G$304,取引!$B$5:$B$304,"売上",取引!$H$5:$H$304,A15) | C15: =SUMIFS(取引!$G$5:$G$304,取引!$B$5:$B$304,"経費",取引!$H$5:$H$304,A15) | D15: =B15-C15
A16: 12 | B16: =SUMIFS(取引!$G$5:$G$304,取引!$B$5:$B$304,"売上",取引!$H$5:$H$304,A16) | C16: =SUMIFS(取引!$G$5:$G$304,取引!$B$5:$B$304,"経費",取引!$H$5:$H$304,A16) | D16: =B16-C16
A17: 年間合計 | B17: =SUM(B5:B16) | C17: =SUM(C5:C16) | D17: =SUM(D5:D16)
A20: 勘定科目(編集可) | B20: 経費計上額 | C20: 支出総額 | D20: 家事按分で除外した額
A21: 通信費 | B21: =SUMIFS(取引!$G$5:$G$304,取引!$B$5:$B$304,"経費",取引!$C$5:$C$304,A21,取引!$H$5:$H$304,">0") | C21: =SUMIFS(取引!$E$5:$E$304,取引!$B$5:$B$304,"経費",取引!$C$5:$C$304,A21,取引!$H$5:$H$304,">0") | D21: =C21-B21
A22: 水道光熱費 | B22: =SUMIFS(取引!$G$5:$G$304,取引!$B$5:$B$304,"経費",取引!$C$5:$C$304,A22,取引!$H$5:$H$304,">0") | C22: =SUMIFS(取引!$E$5:$E$304,取引!$B$5:$B$304,"経費",取引!$C$5:$C$304,A22,取引!$H$5:$H$304,">0") | D22: =C22-B22
A23: 地代家賃 | B23: =SUMIFS(取引!$G$5:$G$304,取引!$B$5:$B$304,"経費",取引!$C$5:$C$304,A23,取引!$H$5:$H$304,">0") | C23: =SUMIFS(取引!$E$5:$E$304,取引!$B$5:$B$304,"経費",取引!$C$5:$C$304,A23,取引!$H$5:$H$304,">0") | D23: =C23-B23
A24: 消耗品費 | B24: =SUMIFS(取引!$G$5:$G$304,取引!$B$5:$B$304,"経費",取引!$C$5:$C$304,A24,取引!$H$5:$H$304,">0") | C24: =SUMIFS(取引!$E$5:$E$304,取引!$B$5:$B$304,"経費",取引!$C$5:$C$304,A24,取引!$H$5:$H$304,">0") | D24: =C24-B24
A25: 旅費交通費 | B25: =SUMIFS(取引!$G$5:$G$304,取引!$B$5:$B$304,"経費",取引!$C$5:$C$304,A25,取引!$H$5:$H$304,">0") | C25: =SUMIFS(取引!$E$5:$E$304,取引!$B$5:$B$304,"経費",取引!$C$5:$C$304,A25,取引!$H$5:$H$304,">0") | D25: =C25-B25
A26: 接待交際費 | B26: =SUMIFS(取引!$G$5:$G$304,取引!$B$5:$B$304,"経費",取引!$C$5:$C$304,A26,取引!$H$5:$H$304,">0") | C26: =SUMIFS(取引!$E$5:$E$304,取引!$B$5:$B$304,"経費",取引!$C$5:$C$304,A26,取引!$H$5:$H$304,">0") | D26: =C26-B26
A27: 外注工賃 | B27: =SUMIFS(取引!$G$5:$G$304,取引!$B$5:$B$304,"経費",取引!$C$5:$C$304,A27,取引!$H$5:$H$304,">0") | C27: =SUMIFS(取引!$E$5:$E$304,取引!$B$5:$B$304,"経費",取引!$C$5:$C$304,A27,取引!$H$5:$H$304,">0") | D27: =C27-B27
A28: 広告宣伝費 | B28: =SUMIFS(取引!$G$5:$G$304,取引!$B$5:$B$304,"経費",取引!$C$5:$C$304,A28,取引!$H$5:$H$304,">0") | C28: =SUMIFS(取引!$E$5:$E$304,取引!$B$5:$B$304,"経費",取引!$C$5:$C$304,A28,取引!$H$5:$H$304,">0") | D28: =C28-B28
A29: 租税公課 | B29: =SUMIFS(取引!$G$5:$G$304,取引!$B$5:$B$304,"経費",取引!$C$5:$C$304,A29,取引!$H$5:$H$304,">0") | C29: =SUMIFS(取引!$E$5:$E$304,取引!$B$5:$B$304,"経費",取引!$C$5:$C$304,A29,取引!$H$5:$H$304,">0") | D29: =C29-B29
A30: 減価償却費 | B30: =SUMIFS(取引!$G$5:$G$304,取引!$B$5:$B$304,"経費",取引!$C$5:$C$304,A30,取引!$H$5:$H$304,">0") | C30: =SUMIFS(取引!$E$5:$E$304,取引!$B$5:$B$304,"経費",取引!$C$5:$C$304,A30,取引!$H$5:$H$304,">0") | D30: =C30-B30
A31: 雑費 | B31: =SUMIFS(取引!$G$5:$G$304,取引!$B$5:$B$304,"経費",取引!$C$5:$C$304,A31,取引!$H$5:$H$304,">0") | C31: =SUMIFS(取引!$E$5:$E$304,取引!$B$5:$B$304,"経費",取引!$C$5:$C$304,A31,取引!$H$5:$H$304,">0") | D31: =C31-B31
A32: その他 | B32: =SUMIFS(取引!$G$5:$G$304,取引!$B$5:$B$304,"経費",取引!$C$5:$C$304,A32,取引!$H$5:$H$304,">0") | C32: =SUMIFS(取引!$E$5:$E$304,取引!$B$5:$B$304,"経費",取引!$C$5:$C$304,A32,取引!$H$5:$H$304,">0") | D32: =C32-B32
A33: 科目合計 | B33: =SUM(B21:B32) | C33: =SUM(C21:C32) | D33: =SUM(D21:D32)
A34: チェック | B34: =IF(B33=C17,"OK: 月次経費と一致","不一致: 科目未設定の経費あり")

Sheet 使い方
A1: 売上・経費管理 使い方
A2: 1. 「年間集計」B2に対象年を入れ、「取引」に1行ずつ入力します(最大300行)。対象年以外の日付の行は集計されません。
A3: 2. 区分=経費の行で『事業割合(%)』を入れると、金額 x 割合 を1円未満切捨てして計上額にします。空欄は100%です。
A4: 3. 勘定科目は「年間集計」A21:A32のリストから選びます。リスト名は編集可能です。
A5: 4. 金額は税込で入力する前提です。消費税の区分・簡易課税・インボイスの仕入税額控除の集計はしません。
A6: 5. 家事按分の割合の妥当性(使用実態に基づく合理的な根拠)は利用者の判断です。税務判断は税理士等へ。
A7: 6. 氏名・金額はすべてダミーです。
